housekeep/__init__.py
housekeep/housekeep.py
ddclearner-1.0.0.dist-info/METADATA
ddclearner-1.0.0.dist-info/WHEEL
ddclearner-1.0.0.dist-info/entry_points.txt
ddclearner-1.0.0.dist-info/licenses/LICENSE
ddclearner-1.0.0.dist-info/RECORD
