Metadata-Version: 2.3
Name: ddclearner
Version: 1.0.0
Summary: Cleanup your directory
Author-email: okdj0201 <j.okada.0201.rec@gmail.com>
License-File: LICENSE
Requires-Python: >=3.9
Requires-Dist: argparse>=1.4.0
Requires-Dist: datetime>=5.5
Requires-Dist: pathlib>=1.0.1
Requires-Dist: pyyaml>=6.0.1
